WebsiteGenerator/__init__.py
WebsiteGenerator/wg.py
by0websitegenerator-5.0.4.dist-info/LICENSE
by0websitegenerator-5.0.4.dist-info/METADATA
by0websitegenerator-5.0.4.dist-info/WHEEL
by0websitegenerator-5.0.4.dist-info/entry_points.txt
by0websitegenerator-5.0.4.dist-info/top_level.txt
by0websitegenerator-5.0.4.dist-info/RECORD
