Metadata-Version: 2.1
Name: by0websitegenerator
Version: 5.0.4
Summary: Make a website in just 5 minutes!
Home-page: https://generator.byzero.dev
Author: byZer0
Author-email: mail@byzero.dev
License: UNKNOWN
Project-URL: Bug Tracker, https://github.com/WebsiteGenerator/WebsiteGenerator/issues
Platform: UNKNOWN
Classifier: Programming Language :: Python :: 3
Classifier: License :: OSI Approved :: MIT License
Classifier: Operating System :: OS Independent
Requires-Python: >=3.6
License-File: LICENSE
